pydomo/DomoAPIClient.py
pydomo/Transport.py
pydomo/__init__.py
pydomo/accounts/AccountClient.py
pydomo/accounts/__init__.py
pydomo/common/DomoObject.py
pydomo/common/__init__.py
pydomo/datasets/DataSetClient.py
pydomo/datasets/DataSetModel.py
pydomo/datasets/__init__.py
pydomo/groups/GroupClient.py
pydomo/groups/GroupsModel.py
pydomo/groups/__init__.py
pydomo/pages/PageClient.py
pydomo/pages/__init__.py
pydomo/streams/StreamClient.py
pydomo/streams/StreamsModel.py
pydomo/streams/__init__.py
pydomo/users/UserClient.py
pydomo/users/UsersModel.py
pydomo/users/__init__.py
pydomo/utilities/UtilitiesClient.py
pydomo/utilities/__init__.py
pydomo-0.3.0.15.dist-info/licenses/LICENSE.txt
pydomo-0.3.0.15.dist-info/METADATA
pydomo-0.3.0.15.dist-info/WHEEL
pydomo-0.3.0.15.dist-info/top_level.txt
pydomo-0.3.0.15.dist-info/RECORD
